dvp_charts/DvpBar.py
dvp_charts/DvpCharts.py
dvp_charts/DvpCharts2.py
dvp_charts/DvpHist.py
dvp_charts/DvpScatter.py
dvp_charts/DvpTemplate.py
dvp_charts/DvpWordCloud.py
dvp_charts/DvpWordGraph.py
dvp_charts/__init__.py
dvp_charts/_imports_ copy.py
dvp_charts/_imports_.py
dvp_charts/async-DvpCharts.js
dvp_charts/async-DvpCharts.js.map
dvp_charts/async-DvpWordCloud.js
dvp_charts/async-DvpWordCloud.js.map
dvp_charts/cleanData.py
dvp_charts/dvp_charts.min.js
dvp_charts/dvp_charts.min.js.map
dvp_charts/metadata.json
dvp_charts/package-info.json
dvp_charts-0.0.1.dist-info/LICENSE
dvp_charts-0.0.1.dist-info/METADATA
dvp_charts-0.0.1.dist-info/WHEEL
dvp_charts-0.0.1.dist-info/top_level.txt
dvp_charts-0.0.1.dist-info/RECORD
